captcha_operation/__init__.py
captcha_operation/operation.py
captcha_operation-0.0.2.dist-info/LICENSE
captcha_operation-0.0.2.dist-info/METADATA
captcha_operation-0.0.2.dist-info/WHEEL
captcha_operation-0.0.2.dist-info/top_level.txt
captcha_operation-0.0.2.dist-info/zip-safe
captcha_operation-0.0.2.dist-info/RECORD
