Metadata-Version: 2.2
Name: captcha_operation
Version: 0.0.2
Summary: 数字运算验证码
Home-page: https://github.com/xiaoxuan6/captcha_operation
Author: xiaoxuan6
Keywords: number operation captcha
Classifier: Programming Language :: Python :: 3.12
Classifier: License :: OSI Approved :: MIT License
Requires-Python: >=3.12
License-File: LICENSE
Requires-Dist: ddddocr
Dynamic: author
Dynamic: classifier
Dynamic: description
Dynamic: description-content-type
Dynamic: home-page
Dynamic: keywords
Dynamic: requires-dist
Dynamic: requires-python
Dynamic: summary
